{
  "feedback": [
    {
      "mode": "feedback",
      "seed": 1000,
      "panel_jitter_x_mm": 1.24,
      "panel_jitter_y_mm": 6.023,
      "success": true,
      "tactile_grasp": true,
      "switch_isolated": true,
      "latch_pressed": true,
      "tag_seated": true,
      "final_switch_angle_deg": 87.065,
      "max_latch_travel_mm": 6.564,
      "final_tag_error_mm": 14.399,
      "peak_touch_force_n": 49.4513,
      "max_alignment_error_mm": 18.201,
      "vision_corrections": 289,
      "recovery_events": 5,
      "contact_samples": 5823,
      "simulated_seconds": 17.0
    },
    {
      "mode": "feedback",
      "seed": 1001,
      "panel_jitter_x_mm": 6.531,
      "panel_jitter_y_mm": -28.089,
      "success": true,
      "tactile_grasp": true,
      "switch_isolated": true,
      "latch_pressed": true,
      "tag_seated": true,
      "final_switch_angle_deg": 87.556,
      "max_latch_travel_mm": 6.564,
      "final_tag_error_mm": 14.749,
      "peak_touch_force_n": 50.7185,
      "max_alignment_error_mm": 17.39,
      "vision_corrections": 295,
      "recovery_events": 4,
      "contact_samples": 5847,
      "simulated_seconds": 17.0
    },
    {
      "mode": "feedback",
      "seed": 1002,
      "panel_jitter_x_mm": -6.912,
      "panel_jitter_y_mm": -8.283,
      "success": true,
      "tactile_grasp": true,
      "switch_isolated": true,
      "latch_pressed": true,
      "tag_seated": true,
      "final_switch_angle_deg": 86.41,
      "max_latch_travel_mm": 6.564,
      "final_tag_error_mm": 13.531,
      "peak_touch_force_n": 50.6519,
      "max_alignment_error_mm": 17.305,
      "vision_corrections": 292,
      "recovery_events": 3,
      "contact_samples": 5744,
      "simulated_seconds": 17.0
    },
    {
      "mode": "feedback",
      "seed": 1003,
      "panel_jitter_x_mm": -18.11,
      "panel_jitter_y_mm": -14.111,
      "success": true,
      "tactile_grasp": true,
      "switch_isolated": true,
      "latch_pressed": true,
      "tag_seated": true,
      "final_switch_angle_deg": 87.52,
      "max_latch_travel_mm": 6.564,
      "final_tag_error_mm": 14.786,
      "peak_touch_force_n": 51.7987,
      "max_alignment_error_mm": 27.311,
      "vision_corrections": 290,
      "recovery_events": 2,
      "contact_samples": 5916,
      "simulated_seconds": 17.0
    },
    {
      "mode": "feedback",
      "seed": 1004,
      "panel_jitter_x_mm": -28.949,
      "panel_jitter_y_mm": -21.451,
      "success": true,
      "tactile_grasp": true,
      "switch_isolated": true,
      "latch_pressed": true,
      "tag_seated": true,
      "final_switch_angle_deg": 86.639,
      "max_latch_travel_mm": 6.564,
      "final_tag_error_mm": 13.761,
      "peak_touch_force_n": 50.0489,
      "max_alignment_error_mm": 16.444,
      "vision_corrections": 290,
      "recovery_events": 3,
      "contact_samples": 5685,
      "simulated_seconds": 17.0
    },
    {
      "mode": "feedback",
      "seed": 1005,
      "panel_jitter_x_mm": -24.231,
      "panel_jitter_y_mm": 24.973,
      "success": true,
      "tactile_grasp": true,
      "switch_isolated": true,
      "latch_pressed": true,
      "tag_seated": true,
      "final_switch_angle_deg": 87.671,
      "max_latch_travel_mm": 6.564,
      "final_tag_error_mm": 14.534,
      "peak_touch_force_n": 50.3752,
      "max_alignment_error_mm": 24.81,
      "vision_corrections": 289,
      "recovery_events": 3,
      "contact_samples": 5928,
      "simulated_seconds": 17.0
    },
    {
      "mode": "feedback",
      "seed": 1006,
      "panel_jitter_x_mm": -9.459,
      "panel_jitter_y_mm": 5.85,
      "success": true,
      "tactile_grasp": true,
      "switch_isolated": true,
      "latch_pressed": true,
      "tag_seated": true,
      "final_switch_angle_deg": 86.509,
      "max_latch_travel_mm": 6.564,
      "final_tag_error_mm": 13.472,
      "peak_touch_force_n": 50.5299,
      "max_alignment_error_mm": 20.026,
      "vision_corrections": 296,
      "recovery_events": 3,
      "contact_samples": 5588,
      "simulated_seconds": 17.0
    },
    {
      "mode": "feedback",
      "seed": 1007,
      "panel_jitter_x_mm": -24.869,
      "panel_jitter_y_mm": 18.327,
      "success": true,
      "tactile_grasp": true,
      "switch_isolated": true,
      "latch_pressed": true,
      "tag_seated": true,
      "final_switch_angle_deg": 86.9,
      "max_latch_travel_mm": 6.564,
      "final_tag_error_mm": 14.036,
      "peak_touch_force_n": 50.8776,
      "max_alignment_error_mm": 31.298,
      "vision_corrections": 293,
      "recovery_events": 4,
      "contact_samples": 5545,
      "simulated_seconds": 17.0
    },
    {
      "mode": "feedback",
      "seed": 1008,
      "panel_jitter_x_mm": -19.299,
      "panel_jitter_y_mm": 18.157,
      "success": true,
      "tactile_grasp": true,
      "switch_isolated": true,
      "latch_pressed": true,
      "tag_seated": true,
      "final_switch_angle_deg": 86.885,
      "max_latch_travel_mm": 6.564,
      "final_tag_error_mm": 13.842,
      "peak_touch_force_n": 49.2322,
      "max_alignment_error_mm": 28.233,
      "vision_corrections": 299,
      "recovery_events": 6,
      "contact_samples": 5590,
      "simulated_seconds": 17.0
    },
    {
      "mode": "feedback",
      "seed": 1009,
      "panel_jitter_x_mm": -25.723,
      "panel_jitter_y_mm": -10.039,
      "success": true,
      "tactile_grasp": true,
      "switch_isolated": true,
      "latch_pressed": true,
      "tag_seated": true,
      "final_switch_angle_deg": 86.316,
      "max_latch_travel_mm": 6.564,
      "final_tag_error_mm": 13.46,
      "peak_touch_force_n": 50.6593,
      "max_alignment_error_mm": 19.489,
      "vision_corrections": 290,
      "recovery_events": 2,
      "contact_samples": 5755,
      "simulated_seconds": 17.0
    },
    {
      "mode": "feedback",
      "seed": 1010,
      "panel_jitter_x_mm": -23.49,
      "panel_jitter_y_mm": 2.077,
      "success": true,
      "tactile_grasp": true,
      "switch_isolated": true,
      "latch_pressed": true,
      "tag_seated": true,
      "final_switch_angle_deg": 87.3,
      "max_latch_travel_mm": 6.564,
      "final_tag_error_mm": 14.367,
      "peak_touch_force_n": 50.8755,
      "max_alignment_error_mm": 22.525,
      "vision_corrections": 290,
      "recovery_events": 3,
      "contact_samples": 6086,
      "simulated_seconds": 17.0
    },
    {
      "mode": "feedback",
      "seed": 1011,
      "panel_jitter_x_mm": -12.521,
      "panel_jitter_y_mm": 3.673,
      "success": true,
      "tactile_grasp": true,
      "switch_isolated": true,
      "latch_pressed": true,
      "tag_seated": true,
      "final_switch_angle_deg": 87.758,
      "max_latch_travel_mm": 6.564,
      "final_tag_error_mm": 15.176,
      "peak_touch_force_n": 51.384,
      "max_alignment_error_mm": 24.863,
      "vision_corrections": 291,
      "recovery_events": 3,
      "contact_samples": 5718,
      "simulated_seconds": 17.0
    },
    {
      "mode": "feedback",
      "seed": 1012,
      "panel_jitter_x_mm": -11.233,
      "panel_jitter_y_mm": 16.278,
      "success": true,
      "tactile_grasp": true,
      "switch_isolated": true,
      "latch_pressed": true,
      "tag_seated": true,
      "final_switch_angle_deg": 86.592,
      "max_latch_travel_mm": 6.564,
      "final_tag_error_mm": 13.661,
      "peak_touch_force_n": 50.7017,
      "max_alignment_error_mm": 24.007,
      "vision_corrections": 293,
      "recovery_events": 2,
      "contact_samples": 5829,
      "simulated_seconds": 17.0
    },
    {
      "mode": "feedback",
      "seed": 1013,
      "panel_jitter_x_mm": 17.081,
      "panel_jitter_y_mm": -24.419,
      "success": true,
      "tactile_grasp": true,
      "switch_isolated": true,
      "latch_pressed": true,
      "tag_seated": true,
      "final_switch_angle_deg": 86.689,
      "max_latch_travel_mm": 6.564,
      "final_tag_error_mm": 13.846,
      "peak_touch_force_n": 50.4246,
      "max_alignment_error_mm": 18.071,
      "vision_corrections": 296,
      "recovery_events": 4,
      "contact_samples": 5599,
      "simulated_seconds": 17.0
    },
    {
      "mode": "feedback",
      "seed": 1014,
      "panel_jitter_x_mm": -3.74,
      "panel_jitter_y_mm": 4.971,
      "success": true,
      "tactile_grasp": true,
      "switch_isolated": true,
      "latch_pressed": true,
      "tag_seated": true,
      "final_switch_angle_deg": 87.235,
      "max_latch_travel_mm": 6.564,
      "final_tag_error_mm": 14.264,
      "peak_touch_force_n": 50.1146,
      "max_alignment_error_mm": 17.084,
      "vision_corrections": 290,
      "recovery_events": 3,
      "contact_samples": 5927,
      "simulated_seconds": 17.0
    },
    {
      "mode": "feedback",
      "seed": 1015,
      "panel_jitter_x_mm": -8.126,
      "panel_jitter_y_mm": 6.21,
      "success": true,
      "tactile_grasp": true,
      "switch_isolated": true,
      "latch_pressed": true,
      "tag_seated": true,
      "final_switch_angle_deg": 87.129,
      "max_latch_travel_mm": 6.564,
      "final_tag_error_mm": 14.057,
      "peak_touch_force_n": 50.5438,
      "max_alignment_error_mm": 20.215,
      "vision_corrections": 295,
      "recovery_events": 4,
      "contact_samples": 5821,
      "simulated_seconds": 17.0
    },
    {
      "mode": "feedback",
      "seed": 1016,
      "panel_jitter_x_mm": -15.776,
      "panel_jitter_y_mm": -3.324,
      "success": true,
      "tactile_grasp": true,
      "switch_isolated": true,
      "latch_pressed": true,
      "tag_seated": true,
      "final_switch_angle_deg": 86.4,
      "max_latch_travel_mm": 6.564,
      "final_tag_error_mm": 13.546,
      "peak_touch_force_n": 50.6892,
      "max_alignment_error_mm": 22.215,
      "vision_corrections": 295,
      "recovery_events": 4,
      "contact_samples": 5540,
      "simulated_seconds": 17.0
    },
    {
      "mode": "feedback",
      "seed": 1017,
      "panel_jitter_x_mm": 24.264,
      "panel_jitter_y_mm": 18.637,
      "success": true,
      "tactile_grasp": true,
      "switch_isolated": true,
      "latch_pressed": true,
      "tag_seated": true,
      "final_switch_angle_deg": 87.718,
      "max_latch_travel_mm": 6.564,
      "final_tag_error_mm": 14.626,
      "peak_touch_force_n": 50.6959,
      "max_alignment_error_mm": 29.468,
      "vision_corrections": 294,
      "recovery_events": 3,
      "contact_samples": 5687,
      "simulated_seconds": 17.0
    },
    {
      "mode": "feedback",
      "seed": 1018,
      "panel_jitter_x_mm": 5.451,
      "panel_jitter_y_mm": -2.612,
      "success": true,
      "tactile_grasp": true,
      "switch_isolated": true,
      "latch_pressed": true,
      "tag_seated": true,
      "final_switch_angle_deg": 86.2,
      "max_latch_travel_mm": 6.564,
      "final_tag_error_mm": 13.362,
      "peak_touch_force_n": 50.6251,
      "max_alignment_error_mm": 15.191,
      "vision_corrections": 293,
      "recovery_events": 3,
      "contact_samples": 5666,
      "simulated_seconds": 17.0
    },
    {
      "mode": "feedback",
      "seed": 1019,
      "panel_jitter_x_mm": -16.418,
      "panel_jitter_y_mm": -6.032,
      "success": true,
      "tactile_grasp": true,
      "switch_isolated": true,
      "latch_pressed": true,
      "tag_seated": true,
      "final_switch_angle_deg": 87.566,
      "max_latch_travel_mm": 6.564,
      "final_tag_error_mm": 14.472,
      "peak_touch_force_n": 50.5352,
      "max_alignment_error_mm": 25.822,
      "vision_corrections": 294,
      "recovery_events": 3,
      "contact_samples": 5821,
      "simulated_seconds": 17.0
    },
    {
      "mode": "feedback",
      "seed": 1020,
      "panel_jitter_x_mm": 4.565,
      "panel_jitter_y_mm": -12.547,
      "success": true,
      "tactile_grasp": true,
      "switch_isolated": true,
      "latch_pressed": true,
      "tag_seated": true,
      "final_switch_angle_deg": 87.463,
      "max_latch_travel_mm": 6.564,
      "final_tag_error_mm": 14.675,
      "peak_touch_force_n": 51.2867,
      "max_alignment_error_mm": 15.809,
      "vision_corrections": 289,
      "recovery_events": 3,
      "contact_samples": 6023,
      "simulated_seconds": 17.0
    },
    {
      "mode": "feedback",
      "seed": 1021,
      "panel_jitter_x_mm": -7.285,
      "panel_jitter_y_mm": -24.311,
      "success": true,
      "tactile_grasp": true,
      "switch_isolated": true,
      "latch_pressed": true,
      "tag_seated": true,
      "final_switch_angle_deg": 86.485,
      "max_latch_travel_mm": 6.564,
      "final_tag_error_mm": 13.558,
      "peak_touch_force_n": 50.8698,
      "max_alignment_error_mm": 22.242,
      "vision_corrections": 294,
      "recovery_events": 3,
      "contact_samples": 5761,
      "simulated_seconds": 17.0
    },
    {
      "mode": "feedback",
      "seed": 1022,
      "panel_jitter_x_mm": -28.969,
      "panel_jitter_y_mm": 24.268,
      "success": true,
      "tactile_grasp": true,
      "switch_isolated": true,
      "latch_pressed": true,
      "tag_seated": true,
      "final_switch_angle_deg": 87.375,
      "max_latch_travel_mm": 6.564,
      "final_tag_error_mm": 14.586,
      "peak_touch_force_n": 54.9724,
      "max_alignment_error_mm": 26.139,
      "vision_corrections": 290,
      "recovery_events": 2,
      "contact_samples": 6063,
      "simulated_seconds": 17.0
    },
    {
      "mode": "feedback",
      "seed": 1023,
      "panel_jitter_x_mm": -9.346,
      "panel_jitter_y_mm": 23.542,
      "success": true,
      "tactile_grasp": true,
      "switch_isolated": true,
      "latch_pressed": true,
      "tag_seated": true,
      "final_switch_angle_deg": 86.848,
      "max_latch_travel_mm": 6.564,
      "final_tag_error_mm": 13.93,
      "peak_touch_force_n": 51.5561,
      "max_alignment_error_mm": 22.366,
      "vision_corrections": 290,
      "recovery_events": 3,
      "contact_samples": 5816,
      "simulated_seconds": 17.0
    },
    {
      "mode": "feedback",
      "seed": 1024,
      "panel_jitter_x_mm": -10.297,
      "panel_jitter_y_mm": -14.016,
      "success": true,
      "tactile_grasp": true,
      "switch_isolated": true,
      "latch_pressed": true,
      "tag_seated": true,
      "final_switch_angle_deg": 86.275,
      "max_latch_travel_mm": 6.564,
      "final_tag_error_mm": 13.39,
      "peak_touch_force_n": 50.7404,
      "max_alignment_error_mm": 18.527,
      "vision_corrections": 298,
      "recovery_events": 4,
      "contact_samples": 5637,
      "simulated_seconds": 17.0
    },
    {
      "mode": "feedback",
      "seed": 1025,
      "panel_jitter_x_mm": 18.625,
      "panel_jitter_y_mm": 7.482,
      "success": true,
      "tactile_grasp": true,
      "switch_isolated": true,
      "latch_pressed": true,
      "tag_seated": true,
      "final_switch_angle_deg": 87.284,
      "max_latch_travel_mm": 6.564,
      "final_tag_error_mm": 14.3,
      "peak_touch_force_n": 50.8186,
      "max_alignment_error_mm": 20.695,
      "vision_corrections": 290,
      "recovery_events": 2,
      "contact_samples": 5857,
      "simulated_seconds": 17.0
    },
    {
      "mode": "feedback",
      "seed": 1026,
      "panel_jitter_x_mm": -19.097,
      "panel_jitter_y_mm": 5.517,
      "success": true,
      "tactile_grasp": true,
      "switch_isolated": true,
      "latch_pressed": true,
      "tag_seated": true,
      "final_switch_angle_deg": 86.934,
      "max_latch_travel_mm": 6.564,
      "final_tag_error_mm": 14.166,
      "peak_touch_force_n": 50.5797,
      "max_alignment_error_mm": 25.2,
      "vision_corrections": 292,
      "recovery_events": 3,
      "contact_samples": 5900,
      "simulated_seconds": 17.0
    },
    {
      "mode": "feedback",
      "seed": 1027,
      "panel_jitter_x_mm": -27.377,
      "panel_jitter_y_mm": 3.604,
      "success": true,
      "tactile_grasp": true,
      "switch_isolated": true,
      "latch_pressed": true,
      "tag_seated": true,
      "final_switch_angle_deg": 87.117,
      "max_latch_travel_mm": 6.564,
      "final_tag_error_mm": 14.449,
      "peak_touch_force_n": 50.7885,
      "max_alignment_error_mm": 24.524,
      "vision_corrections": 290,
      "recovery_events": 2,
      "contact_samples": 5888,
      "simulated_seconds": 17.0
    },
    {
      "mode": "feedback",
      "seed": 1028,
      "panel_jitter_x_mm": 18.338,
      "panel_jitter_y_mm": -6.611,
      "success": true,
      "tactile_grasp": true,
      "switch_isolated": true,
      "latch_pressed": true,
      "tag_seated": true,
      "final_switch_angle_deg": 86.635,
      "max_latch_travel_mm": 6.564,
      "final_tag_error_mm": 13.784,
      "peak_touch_force_n": 50.4589,
      "max_alignment_error_mm": 15.457,
      "vision_corrections": 294,
      "recovery_events": 3,
      "contact_samples": 5684,
      "simulated_seconds": 17.0
    },
    {
      "mode": "feedback",
      "seed": 1029,
      "panel_jitter_x_mm": 19.533,
      "panel_jitter_y_mm": 18.73,
      "success": true,
      "tactile_grasp": true,
      "switch_isolated": true,
      "latch_pressed": true,
      "tag_seated": true,
      "final_switch_angle_deg": 86.491,
      "max_latch_travel_mm": 6.564,
      "final_tag_error_mm": 13.652,
      "peak_touch_force_n": 50.3452,
      "max_alignment_error_mm": 28.805,
      "vision_corrections": 294,
      "recovery_events": 3,
      "contact_samples": 5717,
      "simulated_seconds": 17.0
    },
    {
      "mode": "feedback",
      "seed": 1030,
      "panel_jitter_x_mm": -15.262,
      "panel_jitter_y_mm": -27.539,
      "success": true,
      "tactile_grasp": true,
      "switch_isolated": true,
      "latch_pressed": true,
      "tag_seated": true,
      "final_switch_angle_deg": 86.316,
      "max_latch_travel_mm": 6.564,
      "final_tag_error_mm": 13.432,
      "peak_touch_force_n": 51.6239,
      "max_alignment_error_mm": 26.025,
      "vision_corrections": 291,
      "recovery_events": 2,
      "contact_samples": 5697,
      "simulated_seconds": 17.0
    },
    {
      "mode": "feedback",
      "seed": 1031,
      "panel_jitter_x_mm": 11.169,
      "panel_jitter_y_mm": 26.128,
      "success": true,
      "tactile_grasp": true,
      "switch_isolated": true,
      "latch_pressed": true,
      "tag_seated": true,
      "final_switch_angle_deg": 87.473,
      "max_latch_travel_mm": 6.564,
      "final_tag_error_mm": 14.735,
      "peak_touch_force_n": 50.4528,
      "max_alignment_error_mm": 20.384,
      "vision_corrections": 294,
      "recovery_events": 3,
      "contact_samples": 5948,
      "simulated_seconds": 17.0
    },
    {
      "mode": "feedback",
      "seed": 1032,
      "panel_jitter_x_mm": 21.909,
      "panel_jitter_y_mm": -15.388,
      "success": true,
      "tactile_grasp": true,
      "switch_isolated": true,
      "latch_pressed": true,
      "tag_seated": true,
      "final_switch_angle_deg": 87.665,
      "max_latch_travel_mm": 6.564,
      "final_tag_error_mm": 15.193,
      "peak_touch_force_n": 50.1607,
      "max_alignment_error_mm": 17.998,
      "vision_corrections": 295,
      "recovery_events": 3,
      "contact_samples": 5932,
      "simulated_seconds": 17.0
    },
    {
      "mode": "feedback",
      "seed": 1033,
      "panel_jitter_x_mm": 19.032,
      "panel_jitter_y_mm": 21.634,
      "success": true,
      "tactile_grasp": true,
      "switch_isolated": true,
      "latch_pressed": true,
      "tag_seated": true,
      "final_switch_angle_deg": 86.605,
      "max_latch_travel_mm": 6.564,
      "final_tag_error_mm": 13.737,
      "peak_touch_force_n": 50.2767,
      "max_alignment_error_mm": 26.109,
      "vision_corrections": 290,
      "recovery_events": 3,
      "contact_samples": 5736,
      "simulated_seconds": 17.0
    },
    {
      "mode": "feedback",
      "seed": 1034,
      "panel_jitter_x_mm": 27.855,
      "panel_jitter_y_mm": -19.656,
      "success": true,
      "tactile_grasp": true,
      "switch_isolated": true,
      "latch_pressed": true,
      "tag_seated": true,
      "final_switch_angle_deg": 85.962,
      "max_latch_travel_mm": 6.564,
      "final_tag_error_mm": 13.133,
      "peak_touch_force_n": 50.0426,
      "max_alignment_error_mm": 18.806,
      "vision_corrections": 293,
      "recovery_events": 3,
      "contact_samples": 5644,
      "simulated_seconds": 17.0
    },
    {
      "mode": "feedback",
      "seed": 1035,
      "panel_jitter_x_mm": -10.446,
      "panel_jitter_y_mm": -6.952,
      "success": true,
      "tactile_grasp": true,
      "switch_isolated": true,
      "latch_pressed": true,
      "tag_seated": true,
      "final_switch_angle_deg": 86.467,
      "max_latch_travel_mm": 6.564,
      "final_tag_error_mm": 13.613,
      "peak_touch_force_n": 50.4498,
      "max_alignment_error_mm": 19.776,
      "vision_corrections": 295,
      "recovery_events": 4,
      "contact_samples": 5538,
      "simulated_seconds": 17.0
    }
  ],
  "open_loop": [
    {
      "mode": "open_loop",
      "seed": 1000,
      "panel_jitter_x_mm": 1.24,
      "panel_jitter_y_mm": 6.023,
      "success": true,
      "tactile_grasp": true,
      "switch_isolated": true,
      "latch_pressed": true,
      "tag_seated": true,
      "final_switch_angle_deg": 89.954,
      "max_latch_travel_mm": 6.564,
      "final_tag_error_mm": 17.494,
      "peak_touch_force_n": 166.7822,
      "max_alignment_error_mm": 6.149,
      "vision_corrections": 0,
      "recovery_events": 0,
      "contact_samples": 5853,
      "simulated_seconds": 17.0
    },
    {
      "mode": "open_loop",
      "seed": 1001,
      "panel_jitter_x_mm": 6.531,
      "panel_jitter_y_mm": -28.089,
      "success": false,
      "tactile_grasp": false,
      "switch_isolated": false,
      "latch_pressed": true,
      "tag_seated": false,
      "final_switch_angle_deg": 7.796,
      "max_latch_travel_mm": 6.564,
      "final_tag_error_mm": 35.053,
      "peak_touch_force_n": 344.3335,
      "max_alignment_error_mm": 28.839,
      "vision_corrections": 0,
      "recovery_events": 0,
      "contact_samples": 4000,
      "simulated_seconds": 17.0
    },
    {
      "mode": "open_loop",
      "seed": 1002,
      "panel_jitter_x_mm": -6.912,
      "panel_jitter_y_mm": -8.283,
      "success": false,
      "tactile_grasp": true,
      "switch_isolated": true,
      "latch_pressed": true,
      "tag_seated": false,
      "final_switch_angle_deg": 89.518,
      "max_latch_travel_mm": 6.564,
      "final_tag_error_mm": 25.462,
      "peak_touch_force_n": 166.7822,
      "max_alignment_error_mm": 10.788,
      "vision_corrections": 0,
      "recovery_events": 0,
      "contact_samples": 4902,
      "simulated_seconds": 17.0
    },
    {
      "mode": "open_loop",
      "seed": 1003,
      "panel_jitter_x_mm": -18.11,
      "panel_jitter_y_mm": -14.111,
      "success": false,
      "tactile_grasp": false,
      "switch_isolated": false,
      "latch_pressed": true,
      "tag_seated": false,
      "final_switch_angle_deg": 0.016,
      "max_latch_travel_mm": 6.564,
      "final_tag_error_mm": 32.659,
      "peak_touch_force_n": 340.439,
      "max_alignment_error_mm": 22.959,
      "vision_corrections": 0,
      "recovery_events": 0,
      "contact_samples": 5207,
      "simulated_seconds": 17.0
    },
    {
      "mode": "open_loop",
      "seed": 1004,
      "panel_jitter_x_mm": -28.949,
      "panel_jitter_y_mm": -21.451,
      "success": false,
      "tactile_grasp": false,
      "switch_isolated": false,
      "latch_pressed": true,
      "tag_seated": false,
      "final_switch_angle_deg": 8.999,
      "max_latch_travel_mm": 6.564,
      "final_tag_error_mm": 42.627,
      "peak_touch_force_n": 166.7822,
      "max_alignment_error_mm": 36.03,
      "vision_corrections": 0,
      "recovery_events": 0,
      "contact_samples": 4660,
      "simulated_seconds": 17.0
    },
    {
      "mode": "open_loop",
      "seed": 1005,
      "panel_jitter_x_mm": -24.231,
      "panel_jitter_y_mm": 24.973,
      "success": false,
      "tactile_grasp": false,
      "switch_isolated": true,
      "latch_pressed": true,
      "tag_seated": false,
      "final_switch_angle_deg": 89.821,
      "max_latch_travel_mm": 6.564,
      "final_tag_error_mm": 41.39,
      "peak_touch_force_n": 166.7822,
      "max_alignment_error_mm": 34.796,
      "vision_corrections": 0,
      "recovery_events": 0,
      "contact_samples": 6075,
      "simulated_seconds": 17.0
    },
    {
      "mode": "open_loop",
      "seed": 1006,
      "panel_jitter_x_mm": -9.459,
      "panel_jitter_y_mm": 5.85,
      "success": false,
      "tactile_grasp": true,
      "switch_isolated": true,
      "latch_pressed": true,
      "tag_seated": false,
      "final_switch_angle_deg": 89.041,
      "max_latch_travel_mm": 6.564,
      "final_tag_error_mm": 25.065,
      "peak_touch_force_n": 166.7822,
      "max_alignment_error_mm": 11.121,
      "vision_corrections": 0,
      "recovery_events": 0,
      "contact_samples": 5307,
      "simulated_seconds": 17.0
    },
    {
      "mode": "open_loop",
      "seed": 1007,
      "panel_jitter_x_mm": -24.869,
      "panel_jitter_y_mm": 18.327,
      "success": false,
      "tactile_grasp": false,
      "switch_isolated": false,
      "latch_pressed": true,
      "tag_seated": false,
      "final_switch_angle_deg": 2.191,
      "max_latch_travel_mm": 6.564,
      "final_tag_error_mm": 36.691,
      "peak_touch_force_n": 262.4127,
      "max_alignment_error_mm": 30.892,
      "vision_corrections": 0,
      "recovery_events": 0,
      "contact_samples": 5675,
      "simulated_seconds": 17.0
    },
    {
      "mode": "open_loop",
      "seed": 1008,
      "panel_jitter_x_mm": -19.299,
      "panel_jitter_y_mm": 18.157,
      "success": false,
      "tactile_grasp": false,
      "switch_isolated": false,
      "latch_pressed": true,
      "tag_seated": false,
      "final_switch_angle_deg": 1.897,
      "max_latch_travel_mm": 6.564,
      "final_tag_error_mm": 33.52,
      "peak_touch_force_n": 280.2621,
      "max_alignment_error_mm": 26.498,
      "vision_corrections": 0,
      "recovery_events": 0,
      "contact_samples": 5742,
      "simulated_seconds": 17.0
    },
    {
      "mode": "open_loop",
      "seed": 1009,
      "panel_jitter_x_mm": -25.723,
      "panel_jitter_y_mm": -10.039,
      "success": false,
      "tactile_grasp": false,
      "switch_isolated": false,
      "latch_pressed": true,
      "tag_seated": false,
      "final_switch_angle_deg": -0.102,
      "max_latch_travel_mm": 6.564,
      "final_tag_error_mm": 67.749,
      "peak_touch_force_n": 249.277,
      "max_alignment_error_mm": 27.613,
      "vision_corrections": 0,
      "recovery_events": 0,
      "contact_samples": 6203,
      "simulated_seconds": 17.0
    },
    {
      "mode": "open_loop",
      "seed": 1010,
      "panel_jitter_x_mm": -23.49,
      "panel_jitter_y_mm": 2.077,
      "success": false,
      "tactile_grasp": false,
      "switch_isolated": false,
      "latch_pressed": true,
      "tag_seated": false,
      "final_switch_angle_deg": 4.158,
      "max_latch_travel_mm": 6.564,
      "final_tag_error_mm": 26.827,
      "peak_touch_force_n": 304.7448,
      "max_alignment_error_mm": 23.582,
      "vision_corrections": 0,
      "recovery_events": 0,
      "contact_samples": 5668,
      "simulated_seconds": 17.0
    },
    {
      "mode": "open_loop",
      "seed": 1011,
      "panel_jitter_x_mm": -12.521,
      "panel_jitter_y_mm": 3.673,
      "success": false,
      "tactile_grasp": true,
      "switch_isolated": true,
      "latch_pressed": true,
      "tag_seated": false,
      "final_switch_angle_deg": 88.975,
      "max_latch_travel_mm": 6.564,
      "final_tag_error_mm": 30.308,
      "peak_touch_force_n": 166.7822,
      "max_alignment_error_mm": 13.048,
      "vision_corrections": 0,
      "recovery_events": 0,
      "contact_samples": 5246,
      "simulated_seconds": 17.0
    },
    {
      "mode": "open_loop",
      "seed": 1012,
      "panel_jitter_x_mm": -11.233,
      "panel_jitter_y_mm": 16.278,
      "success": false,
      "tactile_grasp": false,
      "switch_isolated": false,
      "latch_pressed": true,
      "tag_seated": false,
      "final_switch_angle_deg": 21.97,
      "max_latch_travel_mm": 6.564,
      "final_tag_error_mm": 95.6,
      "peak_touch_force_n": 329.1027,
      "max_alignment_error_mm": 19.777,
      "vision_corrections": 0,
      "recovery_events": 0,
      "contact_samples": 6628,
      "simulated_seconds": 17.0
    },
    {
      "mode": "open_loop",
      "seed": 1013,
      "panel_jitter_x_mm": 17.081,
      "panel_jitter_y_mm": -24.419,
      "success": false,
      "tactile_grasp": false,
      "switch_isolated": false,
      "latch_pressed": true,
      "tag_seated": false,
      "final_switch_angle_deg": -0.004,
      "max_latch_travel_mm": 6.564,
      "final_tag_error_mm": 38.016,
      "peak_touch_force_n": 322.3659,
      "max_alignment_error_mm": 29.8,
      "vision_corrections": 0,
      "recovery_events": 0,
      "contact_samples": 3944,
      "simulated_seconds": 17.0
    },
    {
      "mode": "open_loop",
      "seed": 1014,
      "panel_jitter_x_mm": -3.74,
      "panel_jitter_y_mm": 4.971,
      "success": false,
      "tactile_grasp": true,
      "switch_isolated": true,
      "latch_pressed": true,
      "tag_seated": false,
      "final_switch_angle_deg": 89.198,
      "max_latch_travel_mm": 6.564,
      "final_tag_error_mm": 23.768,
      "peak_touch_force_n": 166.7822,
      "max_alignment_error_mm": 6.22,
      "vision_corrections": 0,
      "recovery_events": 0,
      "contact_samples": 5425,
      "simulated_seconds": 17.0
    },
    {
      "mode": "open_loop",
      "seed": 1015,
      "panel_jitter_x_mm": -8.126,
      "panel_jitter_y_mm": 6.21,
      "success": false,
      "tactile_grasp": true,
      "switch_isolated": true,
      "latch_pressed": true,
      "tag_seated": false,
      "final_switch_angle_deg": 89.484,
      "max_latch_travel_mm": 6.564,
      "final_tag_error_mm": 24.97,
      "peak_touch_force_n": 166.7822,
      "max_alignment_error_mm": 10.227,
      "vision_corrections": 0,
      "recovery_events": 0,
      "contact_samples": 5312,
      "simulated_seconds": 17.0
    },
    {
      "mode": "open_loop",
      "seed": 1016,
      "panel_jitter_x_mm": -15.776,
      "panel_jitter_y_mm": -3.324,
      "success": false,
      "tactile_grasp": false,
      "switch_isolated": false,
      "latch_pressed": true,
      "tag_seated": false,
      "final_switch_angle_deg": 4.827,
      "max_latch_travel_mm": 6.564,
      "final_tag_error_mm": 22.927,
      "peak_touch_force_n": 192.3219,
      "max_alignment_error_mm": 16.123,
      "vision_corrections": 0,
      "recovery_events": 0,
      "contact_samples": 5675,
      "simulated_seconds": 17.0
    },
    {
      "mode": "open_loop",
      "seed": 1017,
      "panel_jitter_x_mm": 24.264,
      "panel_jitter_y_mm": 18.637,
      "success": false,
      "tactile_grasp": false,
      "switch_isolated": false,
      "latch_pressed": true,
      "tag_seated": false,
      "final_switch_angle_deg": 43.482,
      "max_latch_travel_mm": 6.564,
      "final_tag_error_mm": 32.153,
      "peak_touch_force_n": 363.1885,
      "max_alignment_error_mm": 30.596,
      "vision_corrections": 0,
      "recovery_events": 0,
      "contact_samples": 4327,
      "simulated_seconds": 17.0
    },
    {
      "mode": "open_loop",
      "seed": 1018,
      "panel_jitter_x_mm": 5.451,
      "panel_jitter_y_mm": -2.612,
      "success": true,
      "tactile_grasp": true,
      "switch_isolated": true,
      "latch_pressed": true,
      "tag_seated": true,
      "final_switch_angle_deg": 89.804,
      "max_latch_travel_mm": 6.564,
      "final_tag_error_mm": 18.48,
      "peak_touch_force_n": 166.7822,
      "max_alignment_error_mm": 6.044,
      "vision_corrections": 0,
      "recovery_events": 0,
      "contact_samples": 5637,
      "simulated_seconds": 17.0
    },
    {
      "mode": "open_loop",
      "seed": 1019,
      "panel_jitter_x_mm": -16.418,
      "panel_jitter_y_mm": -6.032,
      "success": false,
      "tactile_grasp": false,
      "switch_isolated": false,
      "latch_pressed": true,
      "tag_seated": false,
      "final_switch_angle_deg": -0.056,
      "max_latch_travel_mm": 6.564,
      "final_tag_error_mm": 64.323,
      "peak_touch_force_n": 250.0957,
      "max_alignment_error_mm": 17.491,
      "vision_corrections": 0,
      "recovery_events": 0,
      "contact_samples": 6232,
      "simulated_seconds": 17.0
    },
    {
      "mode": "open_loop",
      "seed": 1020,
      "panel_jitter_x_mm": 4.565,
      "panel_jitter_y_mm": -12.547,
      "success": false,
      "tactile_grasp": true,
      "switch_isolated": true,
      "latch_pressed": true,
      "tag_seated": false,
      "final_switch_angle_deg": 86.907,
      "max_latch_travel_mm": 6.564,
      "final_tag_error_mm": 22.003,
      "peak_touch_force_n": 166.7822,
      "max_alignment_error_mm": 13.351,
      "vision_corrections": 0,
      "recovery_events": 0,
      "contact_samples": 5182,
      "simulated_seconds": 17.0
    },
    {
      "mode": "open_loop",
      "seed": 1021,
      "panel_jitter_x_mm": -7.285,
      "panel_jitter_y_mm": -24.311,
      "success": false,
      "tactile_grasp": false,
      "switch_isolated": false,
      "latch_pressed": true,
      "tag_seated": false,
      "final_switch_angle_deg": 7.579,
      "max_latch_travel_mm": 6.564,
      "final_tag_error_mm": 31.347,
      "peak_touch_force_n": 339.3151,
      "max_alignment_error_mm": 25.379,
      "vision_corrections": 0,
      "recovery_events": 0,
      "contact_samples": 4124,
      "simulated_seconds": 17.0
    },
    {
      "mode": "open_loop",
      "seed": 1022,
      "panel_jitter_x_mm": -28.969,
      "panel_jitter_y_mm": 24.268,
      "success": false,
      "tactile_grasp": false,
      "switch_isolated": true,
      "latch_pressed": true,
      "tag_seated": false,
      "final_switch_angle_deg": 90.017,
      "max_latch_travel_mm": 6.564,
      "final_tag_error_mm": 45.219,
      "peak_touch_force_n": 166.7822,
      "max_alignment_error_mm": 37.791,
      "vision_corrections": 0,
      "recovery_events": 0,
      "contact_samples": 6256,
      "simulated_seconds": 17.0
    },
    {
      "mode": "open_loop",
      "seed": 1023,
      "panel_jitter_x_mm": -9.346,
      "panel_jitter_y_mm": 23.542,
      "success": false,
      "tactile_grasp": false,
      "switch_isolated": false,
      "latch_pressed": true,
      "tag_seated": false,
      "final_switch_angle_deg": -0.228,
      "max_latch_travel_mm": 6.564,
      "final_tag_error_mm": 73.299,
      "peak_touch_force_n": 234.6886,
      "max_alignment_error_mm": 25.329,
      "vision_corrections": 0,
      "recovery_events": 0,
      "contact_samples": 6440,
      "simulated_seconds": 17.0
    },
    {
      "mode": "open_loop",
      "seed": 1024,
      "panel_jitter_x_mm": -10.297,
      "panel_jitter_y_mm": -14.016,
      "success": false,
      "tactile_grasp": false,
      "switch_isolated": false,
      "latch_pressed": true,
      "tag_seated": false,
      "final_switch_angle_deg": 3.781,
      "max_latch_travel_mm": 6.564,
      "final_tag_error_mm": 30.243,
      "peak_touch_force_n": 200.1682,
      "max_alignment_error_mm": 17.392,
      "vision_corrections": 0,
      "recovery_events": 0,
      "contact_samples": 4240,
      "simulated_seconds": 17.0
    },
    {
      "mode": "open_loop",
      "seed": 1025,
      "panel_jitter_x_mm": 18.625,
      "panel_jitter_y_mm": 7.482,
      "success": false,
      "tactile_grasp": false,
      "switch_isolated": false,
      "latch_pressed": true,
      "tag_seated": false,
      "final_switch_angle_deg": 18.872,
      "max_latch_travel_mm": 6.564,
      "final_tag_error_mm": 95.106,
      "peak_touch_force_n": 298.1365,
      "max_alignment_error_mm": 20.072,
      "vision_corrections": 0,
      "recovery_events": 0,
      "contact_samples": 5341,
      "simulated_seconds": 17.0
    },
    {
      "mode": "open_loop",
      "seed": 1026,
      "panel_jitter_x_mm": -19.097,
      "panel_jitter_y_mm": 5.517,
      "success": false,
      "tactile_grasp": false,
      "switch_isolated": false,
      "latch_pressed": true,
      "tag_seated": false,
      "final_switch_angle_deg": 21.792,
      "max_latch_travel_mm": 6.564,
      "final_tag_error_mm": 101.832,
      "peak_touch_force_n": 290.1807,
      "max_alignment_error_mm": 19.878,
      "vision_corrections": 0,
      "recovery_events": 0,
      "contact_samples": 6560,
      "simulated_seconds": 17.0
    },
    {
      "mode": "open_loop",
      "seed": 1027,
      "panel_jitter_x_mm": -27.377,
      "panel_jitter_y_mm": 3.604,
      "success": false,
      "tactile_grasp": false,
      "switch_isolated": false,
      "latch_pressed": true,
      "tag_seated": false,
      "final_switch_angle_deg": 22.229,
      "max_latch_travel_mm": 6.564,
      "final_tag_error_mm": 101.793,
      "peak_touch_force_n": 260.9178,
      "max_alignment_error_mm": 27.614,
      "vision_corrections": 0,
      "recovery_events": 0,
      "contact_samples": 6326,
      "simulated_seconds": 17.0
    },
    {
      "mode": "open_loop",
      "seed": 1028,
      "panel_jitter_x_mm": 18.338,
      "panel_jitter_y_mm": -6.611,
      "success": false,
      "tactile_grasp": false,
      "switch_isolated": false,
      "latch_pressed": true,
      "tag_seated": false,
      "final_switch_angle_deg": 0.005,
      "max_latch_travel_mm": 6.564,
      "final_tag_error_mm": 28.145,
      "peak_touch_force_n": 174.6372,
      "max_alignment_error_mm": 19.493,
      "vision_corrections": 0,
      "recovery_events": 0,
      "contact_samples": 4302,
      "simulated_seconds": 17.0
    },
    {
      "mode": "open_loop",
      "seed": 1029,
      "panel_jitter_x_mm": 19.533,
      "panel_jitter_y_mm": 18.73,
      "success": false,
      "tactile_grasp": false,
      "switch_isolated": false,
      "latch_pressed": true,
      "tag_seated": false,
      "final_switch_angle_deg": 56.751,
      "max_latch_travel_mm": 6.564,
      "final_tag_error_mm": 84.244,
      "peak_touch_force_n": 421.9514,
      "max_alignment_error_mm": 27.062,
      "vision_corrections": 0,
      "recovery_events": 0,
      "contact_samples": 5785,
      "simulated_seconds": 17.0
    },
    {
      "mode": "open_loop",
      "seed": 1030,
      "panel_jitter_x_mm": -15.262,
      "panel_jitter_y_mm": -27.539,
      "success": false,
      "tactile_grasp": false,
      "switch_isolated": false,
      "latch_pressed": true,
      "tag_seated": false,
      "final_switch_angle_deg": 7.995,
      "max_latch_travel_mm": 6.564,
      "final_tag_error_mm": 36.8,
      "peak_touch_force_n": 359.8266,
      "max_alignment_error_mm": 31.485,
      "vision_corrections": 0,
      "recovery_events": 0,
      "contact_samples": 4369,
      "simulated_seconds": 17.0
    },
    {
      "mode": "open_loop",
      "seed": 1031,
      "panel_jitter_x_mm": 11.169,
      "panel_jitter_y_mm": 26.128,
      "success": false,
      "tactile_grasp": false,
      "switch_isolated": true,
      "latch_pressed": true,
      "tag_seated": false,
      "final_switch_angle_deg": 90.032,
      "max_latch_travel_mm": 6.564,
      "final_tag_error_mm": 30.875,
      "peak_touch_force_n": 255.4584,
      "max_alignment_error_mm": 28.415,
      "vision_corrections": 0,
      "recovery_events": 0,
      "contact_samples": 6262,
      "simulated_seconds": 17.0
    },
    {
      "mode": "open_loop",
      "seed": 1032,
      "panel_jitter_x_mm": 21.909,
      "panel_jitter_y_mm": -15.388,
      "success": false,
      "tactile_grasp": false,
      "switch_isolated": false,
      "latch_pressed": true,
      "tag_seated": false,
      "final_switch_angle_deg": -0.002,
      "max_latch_travel_mm": 6.564,
      "final_tag_error_mm": 31.571,
      "peak_touch_force_n": 166.7822,
      "max_alignment_error_mm": 26.773,
      "vision_corrections": 0,
      "recovery_events": 0,
      "contact_samples": 3765,
      "simulated_seconds": 17.0
    },
    {
      "mode": "open_loop",
      "seed": 1033,
      "panel_jitter_x_mm": 19.032,
      "panel_jitter_y_mm": 21.634,
      "success": false,
      "tactile_grasp": false,
      "switch_isolated": true,
      "latch_pressed": true,
      "tag_seated": false,
      "final_switch_angle_deg": 90.046,
      "max_latch_travel_mm": 6.564,
      "final_tag_error_mm": 29.195,
      "peak_touch_force_n": 247.7923,
      "max_alignment_error_mm": 28.814,
      "vision_corrections": 0,
      "recovery_events": 0,
      "contact_samples": 6120,
      "simulated_seconds": 17.0
    },
    {
      "mode": "open_loop",
      "seed": 1034,
      "panel_jitter_x_mm": 27.855,
      "panel_jitter_y_mm": -19.656,
      "success": false,
      "tactile_grasp": false,
      "switch_isolated": false,
      "latch_pressed": true,
      "tag_seated": false,
      "final_switch_angle_deg": 0.001,
      "max_latch_travel_mm": 6.564,
      "final_tag_error_mm": 41.295,
      "peak_touch_force_n": 166.7822,
      "max_alignment_error_mm": 34.092,
      "vision_corrections": 0,
      "recovery_events": 0,
      "contact_samples": 3055,
      "simulated_seconds": 17.0
    },
    {
      "mode": "open_loop",
      "seed": 1035,
      "panel_jitter_x_mm": -10.446,
      "panel_jitter_y_mm": -6.952,
      "success": false,
      "tactile_grasp": true,
      "switch_isolated": true,
      "latch_pressed": true,
      "tag_seated": false,
      "final_switch_angle_deg": 89.494,
      "max_latch_travel_mm": 6.564,
      "final_tag_error_mm": 26.314,
      "peak_touch_force_n": 166.7822,
      "max_alignment_error_mm": 12.548,
      "vision_corrections": 0,
      "recovery_events": 0,
      "contact_samples": 4966,
      "simulated_seconds": 17.0
    }
  ]
}